QTube/__init__.py
QTube/scripts/__init__.py
QTube/scripts/qtube.py
QTube/utils/__init__.py
QTube/utils/checks.py
QTube/utils/helpers.py
QTube/utils/parsing.py
QTube/utils/youtube/captions.py
QTube/utils/youtube/channels.py
QTube/utils/youtube/playlists.py
QTube/utils/youtube/videos.py
QTube-2.5.0.dist-info/LICENSE.txt
QTube-2.5.0.dist-info/METADATA
QTube-2.5.0.dist-info/WHEEL
QTube-2.5.0.dist-info/entry_points.txt
QTube-2.5.0.dist-info/top_level.txt
QTube-2.5.0.dist-info/RECORD
