Metadata-Version: 2.1
Name: QTube
Version: 2.5.0
Summary: Automatically add Youtube videos to a playlist.
Home-page: https://github.com/Killian42/QTube
Author: Killian Lebreton
Author-email: Killian Lebreton <killian.lebreton35@gmail.com>
Maintainer-email: Killian Lebreton <killian.lebreton35@gmail.com>
License: MIT License
Project-URL: Homepage, https://github.com/Killian42/QTube
Project-URL: Issues, https://github.com/Killian42/QTube/issues
Project-URL: Repository, https://github.com/Killian42/QTube
Keywords: youtube,videos,playlist,python,python3
Classifier: Development Status :: 5 - Production/Stable
Classifier: License :: OSI Approved :: MIT License
Classifier: Natural Language :: English
Classifier: Programming Language :: Python :: 3
Classifier: Programming Language :: Python :: 3.8
Classifier: Programming Language :: Python :: 3.9
Classifier: Programming Language :: Python :: 3.10
Classifier: Programming Language :: Python :: 3.11
Classifier: Topic :: Multimedia :: Video
Requires-Python: >=3.8
License-File: LICENSE.txt
Requires-Dist: colorama >=0.4.6
Requires-Dist: google-api-python-client >=2.119.0
Requires-Dist: google-auth-oauthlib >=1.0.0
Requires-Dist: isodate >=0.6.1
Requires-Dist: numpy >=1.24.3
Requires-Dist: protobuf >=4.25.1
Requires-Dist: pytube >=15.0.0
Requires-Dist: Requests >=2.32.0
Requires-Dist: setuptools >=70.0.0
